<?xml version="1.0" encoding="UTF-8"?>
<equipo nombre="Rayo Vallecano">
    <jugadores>
        <!-- Porteros -->
        <jugador>
            <nombre>D. Cárdenas</nombre>
            <dorsal>1</dorsal>
            <demarcacion>Portero</demarcacion>
            <nacionalidad>España</nacionalidad>
            <nacimiento>28/03/1997</nacimiento>
            <altura>1.86m</altura>
            <peso>80kg</peso>
        </jugador>
        <jugador>
            <nombre>A. Batalla</nombre>
            <dorsal>13</dorsal>
            <demarcacion>Portero</demarcacion>
            <nacionalidad>Argentina</nacionalidad>
            <nacimiento>30/04/1996</nacimiento>
            <altura>1.86m</altura>
            <peso>87kg</peso>
        </jugador>

        <!-- Defensas -->
        <jugador>
            <nombre>Andrei</nombre>
            <dorsal>2</dorsal>
            <demarcacion>Defensa</demarcacion>
            <nacionalidad>Rumanía</nacionalidad>
            <nacimiento>20/06/1998</nacimiento>
            <altura>1.83m</altura>
            <peso>75kg</peso>
        </jugador>
        <jugador>
            <nombre>Pep Chavarria</nombre>
            <dorsal>3</dorsal>
            <demarcacion>Defensa</demarcacion>
            <nacionalidad>España</nacionalidad>
            <nacimiento>10/04/1998</nacimiento>
            <altura>1.74m</altura>
            <peso>72kg</peso>
        </jugador>
        <jugador>
            <nombre>Aridane</nombre>
            <dorsal>5</dorsal>
            <demarcacion>Defensa</demarcacion>
            <nacionalidad>España</nacionalidad>
            <nacimiento>23/03/1989</nacimiento>
            <altura>1.86m</altura>
            <peso>77kg</peso>
        </jugador>
        <jugador>
            <nombre>A. Mumin</nombre>
            <dorsal>16</dorsal>
            <demarcacion>Defensa</demarcacion>
            <nacionalidad>Ghana</nacionalidad>
            <nacimiento>06/06/1998</nacimiento>
            <altura>1.88m</altura>
            <peso>79kg</peso>
        </jugador>
        <jugador>
            <nombre>Balliu</nombre>
            <dorsal>20</dorsal>
            <demarcacion>Defensa</demarcacion>
            <nacionalidad>Albania</nacionalidad>
            <nacimiento>01/01/1992</nacimiento>
            <altura>1.72m</altura>
            <peso>63kg</peso>
        </jugador>
        <jugador>
            <nombre>Pacha</nombre>
            <dorsal>22</dorsal>
            <demarcacion>Defensa</demarcacion>
            <nacionalidad>Uruguay</nacionalidad>
            <nacimiento>05/01/1992</nacimiento>
            <altura>1.72m</altura>
            <peso>71kg</peso>
        </jugador>
        <jugador>
            <nombre>Lejeune</nombre>
            <dorsal>24</dorsal>
            <demarcacion>Defensa</demarcacion>
            <nacionalidad>Francia</nacionalidad>
            <nacimiento>20/05/1991</nacimiento>
            <altura>1.89m</altura>
            <peso>89kg</peso>
        </jugador>
        <jugador>
            <nombre>De Las Sias</nombre>
            <dorsal>26</dorsal>
            <demarcacion>Defensa</demarcacion>
            <nacionalidad>España</nacionalidad>
            <nacimiento>29/12/2005</nacimiento>
            <altura>-</altura>
            <peso>-</peso>
        </jugador>
        <jugador>
            <nombre>Pelayo</nombre>
            <dorsal>27</dorsal>
            <demarcacion>Defensa</demarcacion>
            <nacionalidad>España</nacionalidad>
            <nacimiento>29/04/2003</nacimiento>
            <altura>1.90m</altura>
            <peso>83kg</peso>
        </jugador>

        <!-- Centrocampistas -->
        <jugador>
            <nombre>Pedro Díaz</nombre>
            <dorsal>4</dorsal>
            <demarcacion>Centrocampista</demarcacion>
            <nacionalidad>España</nacionalidad>
            <nacimiento>05/06/1998</nacimiento>
            <altura>1.80m</altura>
            <peso>75kg</peso>
        </jugador>
        <jugador>
            <nombre>Pathé I. Ciss</nombre>
            <dorsal>6</dorsal>
            <demarcacion>Centrocampista</demarcacion>
            <nacionalidad>Senegal</nacionalidad>
            <nacimiento>16/03/1994</nacimiento>
            <altura>1.86m</altura>
            <peso>71kg</peso>
        </jugador>
        <jugador>
            <nombre>Isi</nombre>
            <dorsal>7</dorsal>
            <demarcacion>Centrocampista</demarcacion>
            <nacionalidad>España</nacionalidad>
            <nacimiento>27/12/1994</nacimiento>
            <altura>1.69m</altura>
            <peso>71kg</peso>
        </jugador>
        <jugador>
            <nombre>James</nombre>
            <dorsal>10</dorsal>
            <demarcacion>Centrocampista</demarcacion>
            <nacionalidad>Colombia</nacionalidad>
            <nacimiento>12/07/1991</nacimiento>
            <altura>1.80m</altura>
            <peso>75kg</peso>
        </jugador>
        <jugador>
            <nombre>Nteka</nombre>
            <dorsal>11</dorsal>
            <demarcacion>Centrocampista</demarcacion>
            <nacionalidad>Angola</nacionalidad>
            <nacimiento>06/12/1997</nacimiento>
            <altura>1.89m</altura>
            <peso>75kg</peso>
        </jugador>
        <jugador>
            <nombre>Gumbau</nombre>
            <dorsal>15</dorsal>
            <demarcacion>Centrocampista</demarcacion>
            <nacionalidad>España</nacionalidad>
            <nacimiento>18/12/1994</nacimiento>
            <altura>1.87m</altura>
            <peso>77kg</peso>
        </jugador>
        <jugador>
            <nombre>Unai Lopez</nombre>
            <dorsal>17</dorsal>
            <demarcacion>Centrocampista</demarcacion>
            <nacionalidad>España</nacionalidad>
            <nacimiento>30/10/1995</nacimiento>
            <altura>1.70m</altura>
            <peso>68kg</peso>
        </jugador>
        <jugador>
            <nombre>Álvaro</nombre>
            <dorsal>18</dorsal>
            <demarcacion>Centrocampista</demarcacion>
            <nacionalidad>España</nacionalidad>
            <nacimiento>27/10/1992</nacimiento>
            <altura>1.67m</altura>
            <peso>61kg</peso>
        </jugador>
        <jugador>
            <nombre>De Frutos</nombre>
            <dorsal>19</dorsal>
            <demarcacion>Centrocampista</demarcacion>
            <nacionalidad>España</nacionalidad>
            <nacimiento>20/02/1997</nacimiento>
            <altura>1.73m</altura>
            <peso>72kg</peso>
        </jugador>
        <jugador>
            <nombre>Óscar V.</nombre>
            <dorsal>23</dorsal>
            <demarcacion>Centrocampista</demarcacion>
            <nacionalidad>España</nacionalidad>
            <nacimiento>20/08/1994</nacimiento>
            <altura>1.77m</altura>
            <peso>72kg</peso>
        </jugador>
        <jugador>
            <nombre>Joni M. C.</nombre>
            <dorsal>25</dorsal>
            <demarcacion>Centrocampista</demarcacion>
            <nacionalidad>España</nacionalidad>
            <nacimiento>03/09/1998</nacimiento>
            <altura>1.73m</altura>
            <peso>67kg</peso>
        </jugador>

        <!-- Delanteros -->
        <jugador>
            <nombre>TJP</nombre>
            <dorsal>8</dorsal>
            <demarcacion>Delantero</demarcacion>
            <nacionalidad>Argentina</nacionalidad>
            <nacimiento>26/04/1988</nacimiento>
            <altura>1.80m</altura>
            <peso>79kg</peso>
        </jugador>
        <jugador>
            <nombre>RDT</nombre>
            <dorsal>9</dorsal>
            <demarcacion>Delantero</demarcacion>
            <nacionalidad>España</nacionalidad>
            <nacimiento>17/10/1994</nacimiento>
            <altura>1.80m</altura>
            <peso>72kg</peso>
        </jugador>
        <jugador>
            <nombre>Guardiola L.R</nombre>
            <dorsal>12</dorsal>
            <demarcacion>Delantero</demarcacion>
            <nacionalidad>España</nacionalidad>
            <nacimiento>29/05/1991</nacimiento>
            <altura>1.84m</altura>
            <peso>78kg</peso>
        </jugador>
        <jugador>
            <nombre>Camello</nombre>
            <dorsal>14</dorsal>
            <demarcacion>Delantero</demarcacion>
            <nacionalidad>España</nacionalidad>
            <nacimiento>10/02/2001</nacimiento>
            <altura>1.77m</altura>
            <peso>69kg</peso>
        </jugador>
        <jugador>
            <nombre>Embarba</nombre>
            <dorsal>21</dorsal>
            <demarcacion>Delantero</demarcacion>
            <nacionalidad>España</nacionalidad>
            <nacimiento>07/05/1992</nacimiento>
            <altura>1.73m</altura>
            <peso>66kg</peso>
        </jugador>
        <jugador>
            <nombre>E. Eto'o</nombre>
            <dorsal>28</dorsal>
            <demarcacion>Delantero</demarcacion>
            <nacionalidad>Camerún</nacionalidad>
            <nacimiento>18/08/2002</nacimiento>
            <altura>1.89m</altura>
            <peso>-</peso>
        </jugador>
    </jugadores>
</equipo>
